ideal/__init__.py
ideal/client.py
ideal/conf.py
ideal/exceptions.py
ideal/security.py
ideal/utils.py
ideal/contrib/__init__.py
ideal/contrib/django/__init__.py
ideal/contrib/django/ideal_compat/__init__.py
ideal/contrib/django/ideal_compat/apps.py
ideal/contrib/django/ideal_compat/models.py
ideal/contrib/django/ideal_compat/test_urls.py
ideal/contrib/django/ideal_compat/utils.py
ideal/contrib/django/ideal_compat/views.py
ideal/contrib/django/ideal_compat/management/__init__.py
ideal/contrib/django/ideal_compat/management/commands/__init__.py
ideal/contrib/django/ideal_compat/management/commands/sync_issuers.py
ideal/contrib/django/ideal_compat/migrations/0001_initial.py
ideal/contrib/django/ideal_compat/migrations/__init__.py
ideal/contrib/django/ideal_compat/static/ideal/img/ideal_logo.gif
ideal/contrib/django/ideal_compat/templates/ideal/tests/base.html
ideal/contrib/django/ideal_compat/templates/ideal/tests/get_issuers.html
ideal/contrib/django/ideal_compat/templates/ideal/tests/get_transaction_status.html
ideal/contrib/django/ideal_compat/templates/ideal/tests/index.html
ideal/contrib/django/ideal_compat/templates/ideal/tests/start_transaction.html
ideal/templates/directory_request.xml
ideal/templates/signature.xml
ideal/templates/signed_info.xml
ideal/templates/transaction_request.xml
ideal/templates/transaction_status_request.xml
ideal/tests/__init__.py
ideal/tests/test_client.py
ideal/tests/test_conf.py
ideal/tests/test_security.py
ideal/tests/mock_responses/ideal_directory_response.xml
ideal/tests/mock_responses/ideal_error_response.xml
ideal/tests/mock_responses/ideal_transaction_response.xml
ideal/tests/mock_responses/ideal_transaction_status_response.xml
ideal-0.3.0.dist-info/DESCRIPTION.rst
ideal-0.3.0.dist-info/METADATA
ideal-0.3.0.dist-info/RECORD
ideal-0.3.0.dist-info/WHEEL
ideal-0.3.0.dist-info/metadata.json
ideal-0.3.0.dist-info/top_level.txt
