Metadata-Version: 2.0
Name: ideal
Version: 0.3.0
Summary: Implementation of the iDEAL v3.3.1 specification in Python.
Home-page: https://github.com/maykinmedia/python-ideal
Author: Joeri Bekker
Author-email: joeri@maykinmedia.nl
License: MIT
Keywords: python ideal django
Platform: any
Classifier: Development Status :: 5 - Production/Stable
Classifier: License :: OSI Approved :: MIT License
Classifier: Programming Language :: Python
Classifier: Programming Language :: Python :: 2
Classifier: Programming Language :: Python :: 2.7
Classifier: Programming Language :: Python :: 3
Classifier: Programming Language :: Python :: 3.5
Classifier: Programming Language :: Python :: 3.6
Classifier: Programming Language :: Python :: Implementation :: CPython
Classifier: Framework :: Django
Classifier: Framework :: Django :: 1.8
Classifier: Framework :: Django :: 1.11
Classifier: Framework :: Django :: 2.0
Classifier: Operating System :: OS Independent
Classifier: Topic :: Communications
Classifier: Topic :: System :: Distributed Computing
Classifier: Topic :: Software Development :: Libraries :: Python Modules
Requires-Dist: requests (>=1.2.0)
Requires-Dist: lxml
Requires-Dist: python-dateutil
Requires-Dist: pyOpenSSL
Requires-Dist: six
